dynamic_sites/.gitignore
dynamic_sites/__init__.py
dynamic_sites/admin.py
dynamic_sites/apps.py
dynamic_sites/functions.py
dynamic_sites/models.py
dynamic_sites/signals.py
dynamic_sites/tests.py
dynamic_sites/translation.py
dynamic_sites/urls.py
dynamic_sites/views.py
dynamic_sites/locale/de/LC_MESSAGES/django.mo
dynamic_sites/locale/de/LC_MESSAGES/django.po
dynamic_sites/locale/en/LC_MESSAGES/django.mo
dynamic_sites/locale/en/LC_MESSAGES/django.po
dynamic_sites/management/commands/init_dynamic_sites.py
dynamic_sites/migrations/0001_initial.py
dynamic_sites/migrations/0002_auto_20210211_1142.py
dynamic_sites/migrations/__init__.py
dynamic_sites/templates/dynamic_sites/default.html
dynamic_sites/templates/dynamic_sites/fractures/listmenu_translation.html
django_dynamic_sites-1.1.0.dist-info/AUTHORS.rst
django_dynamic_sites-1.1.0.dist-info/LICENSE
django_dynamic_sites-1.1.0.dist-info/METADATA
django_dynamic_sites-1.1.0.dist-info/WHEEL
django_dynamic_sites-1.1.0.dist-info/top_level.txt
django_dynamic_sites-1.1.0.dist-info/RECORD
