Metadata-Version: 2.1
Name: django-dynamic-sites
Version: 1.1.0
Summary: A django application, which implements a flexible and generic viewsystem providing a convenient way to handle staticpages, model based pages and much more.
Home-page: https://github.com/oruehenbeck/django_dynamic_sites
Author: Jan Müller
Author-email: jmueller@bona-fide.it
License: MIT
Project-URL: Documentation, https://django-dynamic-sites.readthedocs.io/
Project-URL: Changelog, https://django-dynamic-sites.readthedocs.io/en/latest/changelog.html
Project-URL: Issue Tracker, https://github.com/oruehenbeck/django_dynamic_sites/issues
Platform: UNKNOWN
Classifier: Development Status :: 5 - Production/Stable
Classifier: Intended Audience :: Developers
Classifier: License :: OSI Approved :: MIT License
Classifier: Operating System :: Unix
Classifier: Operating System :: POSIX
Classifier: Operating System :: Microsoft :: Windows
Classifier: Programming Language :: Python
Classifier: Programming Language :: Python :: 3
Classifier: Programming Language :: Python :: 3 :: Only
Classifier: Programming Language :: Python :: 3.6
Classifier: Programming Language :: Python :: 3.7
Classifier: Programming Language :: Python :: 3.8
Classifier: Programming Language :: Python :: 3.9
Classifier: Topic :: Utilities
Requires-Python: >=3.6
